kssrag/__init__.py
kssrag/cli.py
kssrag/config.py
kssrag/kssrag.py
kssrag/server.py
kssrag/core/__init__.py
kssrag/core/agents.py
kssrag/core/chunkers.py
kssrag/core/retrievers.py
kssrag/core/vectorstores.py
kssrag/models/__init__.py
kssrag/models/local_llms.py
kssrag/models/openrouter.py
kssrag/utils/__init__.py
kssrag/utils/document_loaders.py
kssrag/utils/helpers.py
kssrag/utils/ocr.py
kssrag/utils/ocr_loader.py
kssrag/utils/preprocessors.py
tests/__init__.py
tests/test_basic.py
tests/test_bm25s.py
tests/test_config.py
tests/test_image_chunker.py
tests/test_integration.py
tests/test_ocr.py
tests/test_streaming.py
tests/test_vectorstores.py
kssrag-0.2.3.dist-info/METADATA
kssrag-0.2.3.dist-info/WHEEL
kssrag-0.2.3.dist-info/entry_points.txt
kssrag-0.2.3.dist-info/top_level.txt
kssrag-0.2.3.dist-info/RECORD
