Metadata-Version: 2.4
Name: kssrag
Version: 0.2.3
Summary: A flexible Retrieval-Augmented Generation framework by Ksschkw
Home-page: https://github.com/Ksschkw/kssrag
Author: Ksschkw
Author-email: kookafor893@gmail.com
Project-URL: Bug Reports, https://github.com/Ksschkw/kssrag/issues
Project-URL: Source, https://github.com/Ksschkw/kssrag
Project-URL: Documentation, https://github.com/Ksschkw/kssrag/docs
Keywords: rag,retrieval,generation,ai,nlp,faiss,bm25
Classifier: Development Status :: 3 - Alpha
Classifier: Intended Audience :: Developers
Classifier: Topic :: Scientific/Engineering :: Artificial Intelligence
Classifier: License :: OSI Approved :: MIT License
Classifier: Programming Language :: Python :: 3
Classifier: Programming Language :: Python :: 3.8
Classifier: Programming Language :: Python :: 3.9
Classifier: Programming Language :: Python :: 3.10
Classifier: Programming Language :: Python :: 3.11
Classifier: Programming Language :: Python :: 3.12
Classifier: Programming Language :: Python :: 3.13
Requires-Python: >=3.8, <4
Requires-Dist: fastapi>=0.104.0
Requires-Dist: uvicorn>=0.24.0
Requires-Dist: python-dotenv>=1.0.0
Requires-Dist: requests>=2.31.0
Requires-Dist: rank-bm25>=0.2.2
Requires-Dist: numpy>=1.26.0
Requires-Dist: faiss-cpu>=1.7.0
Requires-Dist: sentence-transformers>=3.0.0
Requires-Dist: pydantic>=2.0.0
Requires-Dist: pydantic-settings>=2.0.0
Requires-Dist: rapidfuzz>=3.0.0
Requires-Dist: python-multipart>=0.0.6
Requires-Dist: pypdf>=3.0.0
Requires-Dist: scikit-learn>=1.0.0
Requires-Dist: scipy>=1.7.0
Requires-Dist: bm25s>=0.2.14
Requires-Dist: stemmer>=0.0.4
Requires-Dist: pystemmer>=3.0.0
Requires-Dist: python-docx>=1.1.0
Requires-Dist: openpyxl>=3.1.5
Requires-Dist: python-pptx>=1.0.2
Provides-Extra: dev
Requires-Dist: pytest; extra == "dev"
Requires-Dist: black; extra == "dev"
Requires-Dist: flake8; extra == "dev"
Requires-Dist: mypy; extra == "dev"
Provides-Extra: gpu
Requires-Dist: faiss-gpu>=1.7.0; extra == "gpu"
Provides-Extra: all
Requires-Dist: faiss-gpu>=1.7.0; extra == "all"
Requires-Dist: sentence-transformers[gpu]; extra == "all"
Provides-Extra: ocr
Requires-Dist: paddleocr>=2.7.0; extra == "ocr"
Requires-Dist: paddlepaddle>=2.5.0; extra == "ocr"
Requires-Dist: pytesseract>=0.3.10; extra == "ocr"
Requires-Dist: Pillow>=10.0.0; extra == "ocr"
Requires-Dist: opencv-python>=4.8.0; extra == "ocr"
Provides-Extra: office
Requires-Dist: python-docx>=1.1.0; extra == "office"
Requires-Dist: openpyxl>=3.1.0; extra == "office"
Requires-Dist: python-pptx>=0.6.23; extra == "office"
Provides-Extra: faiss
Requires-Dist: faiss-cpu>=1.7.0; sys_platform != "win32" and extra == "faiss"
Requires-Dist: faiss-cpu-win; sys_platform == "win32" and extra == "faiss"
Dynamic: author
Dynamic: author-email
Dynamic: classifier
Dynamic: description
Dynamic: description-content-type
Dynamic: home-page
Dynamic: keywords
Dynamic: project-url
Dynamic: provides-extra
Dynamic: requires-dist
Dynamic: requires-python
Dynamic: summary
